gebpy/__init__.py
gebpy/adapters/__init__.py
gebpy/cli/__init__.py
gebpy/core/__init__.py
gebpy/core/chemistry/__init__.py
gebpy/core/chemistry/common.py
gebpy/core/chemistry/elements.py
gebpy/core/chemistry/geochemistry.py
gebpy/core/fluids/__init__.py
gebpy/core/io/__init__.py
gebpy/core/mathematics/__init__.py
gebpy/core/minerals/__init__.py
gebpy/core/minerals/carbonates.py
gebpy/core/minerals/common.py
gebpy/core/minerals/config.py
gebpy/core/minerals/cyclosilicates.py
gebpy/core/minerals/halides.py
gebpy/core/minerals/inosilicates.py
gebpy/core/minerals/nesosilicates.py
gebpy/core/minerals/organics.py
gebpy/core/minerals/oxides.py
gebpy/core/minerals/phosphates.py
gebpy/core/minerals/phospides.py
gebpy/core/minerals/phyllosilicates.py
gebpy/core/minerals/sorosilicates.py
gebpy/core/minerals/sulfates.py
gebpy/core/minerals/sulfides.py
gebpy/core/minerals/synthesis.py
gebpy/core/minerals/tectosilicates.py
gebpy/core/physics/__init__.py
gebpy/core/physics/common.py
gebpy/core/physics/geophysics.py
gebpy/core/rocks/__init__.py
gebpy/core/rocks/anisotropic_rocks.py
gebpy/core/rocks/common.py
gebpy/core/rocks/config.py
gebpy/core/rocks/isotropic_rocks.py
gebpy/core/subsurface/__init__.py
gebpy/data_minerals/__init__.py
gebpy/data_minerals/acanthite.yaml
gebpy/data_minerals/albite.yaml
gebpy/data_minerals/anatase.yaml
gebpy/data_minerals/ankerite.yaml
gebpy/data_minerals/annite.yaml
gebpy/data_minerals/anorthite.yaml
gebpy/data_minerals/antigorite.yaml
gebpy/data_minerals/aragonite.yaml
gebpy/data_minerals/argutite.yaml
gebpy/data_minerals/arsenolite.yaml
gebpy/data_minerals/au3oxide.yaml
gebpy/data_minerals/avicennite.yaml
gebpy/data_minerals/azurite.yaml
gebpy/data_minerals/baddeleyite.yaml
gebpy/data_minerals/bismite.yaml
gebpy/data_minerals/boehmite.yaml
gebpy/data_minerals/bornite.yaml
gebpy/data_minerals/brookite.yaml
gebpy/data_minerals/brucite.yaml
gebpy/data_minerals/bunsenite.yaml
gebpy/data_minerals/calcite.yaml
gebpy/data_minerals/cassiterite.yaml
gebpy-1.1.16.dist-info/LICENSE
gebpy-1.1.16.dist-info/METADATA
gebpy-1.1.16.dist-info/WHEEL
gebpy-1.1.16.dist-info/entry_points.txt
gebpy-1.1.16.dist-info/top_level.txt
gebpy-1.1.16.dist-info/RECORD
