Metadata-Version: 2.1
Name: gebpy
Version: 1.1.16
Summary: GebPy is a Python-based, open source tool for the generation of geological data of minerals, rocks and complete lithological sequences.
Home-page: https://github.com/MABeeskow/GebPy
Author: Maximilian Alexander Beeskow
Author-email: maximilian.beeskow@rwth-aachen.com
License: LGPL-3.0
Keywords: geophysics,geochemistry,mineralogy,petrology,seismology,stratigraphy,geology,geosciences
License-File: LICENSE
Requires-Dist: numpy
Requires-Dist: scipy
Requires-Dist: pandas
Requires-Dist: matplotlib
